setup.py
djang_io.egg-info/PKG-INFO
djang_io.egg-info/SOURCES.txt
djang_io.egg-info/dependency_links.txt
djang_io.egg-info/requires.txt
djang_io.egg-info/top_level.txt
djangio/__init__.py
djangio/management/__init__.py
djangio/management/commands/__init__.py
djangio/management/commands/runsocketserver.py