Metadata-Version: 1.0
Name: djang-io
Version: 0.4
Summary: SocketIO integration for Django
Home-page: http://github.com/derek-schultz/djang-io
Author: Derek Schultz and D. P. Bulger
Author-email: derek@quiet.af
License: MIT
Platform: any
